LICENSE.txt
MANIFEST.in
README.rst
requirements-dev.txt
requirements.txt
setup.py
GIP/GeoAlgorithms.cpp
GIP/GeoImage.cpp
GIP/GeoRaster.cpp
GIP/GeoResource.cpp
GIP/GeoVectorResource.cpp
GIP/gip.cpp
GIP/cimg/CImg.h
GIP/cimg/convolve.h
GIP/cimg/skeleton.h
GIP/cimg/skeletonize.h
GIP/gip/DataType.h
GIP/gip/GeoAlgorithms.h
GIP/gip/GeoFeature.h
GIP/gip/GeoImage.h
GIP/gip/GeoRaster.h
GIP/gip/GeoResource.h
GIP/gip/GeoVector.h
GIP/gip/GeoVectorResource.h
GIP/gip/geometry.h
GIP/gip/gip.h
GIP/gip/utils.h
GIP/unused/GeoImages.cpp
GIP/unused/GeoImages.h
GIP/unused/GeoSpatialContext.cpp
GIP/unused/GeoSpatialContext.h
GIP/unused/algorithms.cpp
GIP/unused/geoimage.cpp
GIP/unused/tests.cpp
GIP/unused/tests.h
docs/Makefile
docs/algorithms.rst
docs/conf.py
docs/index.rst
docs/install.rst
docs/quickstart.rst
gippy/__init__.py
gippy/_algorithms.so
gippy/_gippy.so
gippy/algorithms.i
gippy/algorithms.py
gippy/algorithms_wrap.cpp
gippy/cimg.i
gippy/gippy.i
gippy/gippy.py
gippy/gippy_wrap.cpp
gippy/libgip.so
gippy/test.py
gippy/version.py
gippy/version.pyc
gippy.egg-info/PKG-INFO
gippy.egg-info/SOURCES.txt
gippy.egg-info/dependency_links.txt
gippy.egg-info/requires.txt
gippy.egg-info/top_level.txt
test/test_GeoAlgorithms.py
test/test_GeoImage.py
test/test_GeoRaster.py
test/test_GeoResource.py