Metadata-Version: 1.1
Name: gippy
Version: 1.0.0
Summary: Geospatial Image Processing for Python
Home-page: UNKNOWN
Author: Matthew Hanson
Author-email: matt.a.hanson@gmail.com
License: Apache v2.0
Platform: UNKNOWN
Classifier: License :: OSI Approved :: Apache Software License
Classifier: Programming Language :: C++
Classifier: Programming Language :: Python
Classifier: Programming Language :: Python :: 2.7
Classifier: Programming Language :: Python :: 3.4
Classifier: Programming Language :: Python :: 3.5
